LICENSE
MANIFEST.in
README.rst
production-taskrc
production.ini
setup.py
mattd/__init__.py
mattd.d/main.ini
mattd.d/taskwarrior.ini
mattd.plugins.taskwarrior.egg-info/PKG-INFO
mattd.plugins.taskwarrior.egg-info/SOURCES.txt
mattd.plugins.taskwarrior.egg-info/dependency_links.txt
mattd.plugins.taskwarrior.egg-info/entry_points.txt
mattd.plugins.taskwarrior.egg-info/namespace_packages.txt
mattd.plugins.taskwarrior.egg-info/not-zip-safe
mattd.plugins.taskwarrior.egg-info/requires.txt
mattd.plugins.taskwarrior.egg-info/top_level.txt
mattd/plugins/__init__.py
mattd/plugins/taskwarrior/__init__.py