Metadata-Version: 1.0
Name: mattd.plugins.taskwarrior
Version: 0.0.6
Summary: Taskwarrior plugin for Matt Daemon
Home-page: http://mattd.rtfd.org/
Author: Ralph Bean
Author-email: rbean@redhat.com
License: AGPLv3+
Platform: UNKNOWN
